[
    {
        "title": "1. Introduction",
        "file": "./100.basic/100.introduction.md",
        "children": [
            {
                "title": "1.1. Base",
                "file": "./100.basic/110.base.md"
            },
            {
                "title": "1.2. Global components",
                "file": "./100.basic/120.components.md"
            },
            {
                "title": "1.3. Technology",
                "file": "./100.basic/130.technology.md"
            },
            {
                "title": "1.4. Implementation",
                "file": "./100.basic/140.implementation.md"
            },
            {
                "title": "1.5. Build",
                "file": "./100.basic/150.build.md"
            },
            {
                "title": "1.6. Languages",
                "file": "./100.basic/160.languages.md"
            },
            {
                "title": "1.7. Images",
                "file": "./100.basic/170.images.md"
            },
            {
                "title": "1.8. Project Customization",
                "file": "./100.basic/180.project-customization.md"
            },
            {
                "title": "1.9. Banners",
                "file": "./100.basic/190.banners.md"
            }
        ]
    },
    {
        "title": "2. Global structure",
        "file": "./200.structure/200.structure.md"
    },
    {
        "title": "3. Config",
        "file": "./300.config/300.config.md",
        "children": [
            {
                "title": "3.1. Backend config",
                "file": "./300.config/310.backend/310.backend-config.md"
            },
            {
                "title": "3.2. Frontend config",
                "file": "./300.config/320.frontend/320.frontend-config.md",
                "children": [
                    {
                        "title": "3.2.1. Base config",
                        "file": "./300.config/320.frontend/321.base/321.base-config.md"
                    },
                    {
                        "title": "3.2.2. Layouts config",
                        "file": "./300.config/320.frontend/322.layouts/322.layouts-config.md"
                    },
                    {
                        "title": "3.2.3. Modules config",
                        "file": "./300.config/320.frontend/323.modules/323.modules-config.md"
                    },
                    {
                        "title": "3.2.4. Files config",
                        "file": "./300.config/320.frontend/324.files/324.files-config.md"
                    },
                    {
                        "title": "3.2.5. Menu",
                        "file": "./300.config/320.frontend/325.menu/325.menu-config.md",
                        "children": [
                            {
                                "title": "3.2.5.1. Main menu",
                                "file": "./300.config/320.frontend/325.menu/3251.main-menu.md"
                            },
                            {
                                "title": "3.2.5.2. Categories menu",
                                "file": "./300.config/320.frontend/325.menu/3252.menu-category.md"
                            },
                            {
                                "title": "3.2.5.3. Mobile menu",
                                "file": "./300.config/320.frontend/325.menu/3253.mobile-menu.md"
                            },
                            {
                                "title": "3.2.5.4. Customizing menu icons",
                                "file": "./300.config/320.frontend/325.menu/3254.menu-icons-setup.md"
                            },
                            {
                                "title": "3.2.5.5. Post menu",
                                "file": "./300.config/320.frontend/325.menu/3255.post-menu.md"
                            },
                            {
                                "title": "3.2.5.6. Profile menu",
                                "file": "./300.config/320.frontend/325.menu/3256.profile-menu.md"
                            },
                            {
                                "title": "3.2.5.7. Burger panel header menu",
                                "file": "./300.config/320.frontend/325.menu/3257.burger-panel-header-menu.md"
                            }
                        ]
                    },
                    {
                        "title": "3.2.6. Fundist menu and category settings control",
                        "file": "./300.config/320.frontend/326.fundist-menu-and-categories/326.fundist-menu-and-categories.md",
                        "children": [
                            {
                                "title": "3.2.6.1. By project config",
                                "file": "./300.config/320.frontend/326.fundist-menu-and-categories/3261.by-project-config.md"
                            }
                        ]
                    },
                    {
                        "title": "3.2.7. Betradar sportsbook settings",
                        "file": "./300.config/320.frontend/327.sportsbook/327.sportsbook-config.md"
                    }
                ]
            }
        ]
    },
    {
        "title": "4. Modules",
        "file": "./400.modules/400.modules.md",
        "children": [
            {
                "title": "4.1. Modules implementation",
                "file": "./400.modules/410.modules-implementation.md"
            }
        ]
    },
    {
        "title": "5. Components",
        "file": "./500.components/500.components.md",
        "children": [
            {
                "title": "5.1. Standard component",
                "file": "./500.components/510.standard-component.md"
            },
            {
                "title": "5.2. Params",
                "file": "./500.components/520.component-params.md"
            },
            {
                "title": "5.3. Template",
                "file": "./500.components/530.component-template.md"
            },
            {
                "title": "5.4. Styles",
                "file": "./500.components/540.component-styles.md"
            },
            {
                "title": "5.5. Customization",
                "file": "./500.components/550.component-customization.md"
            },
            {
                "title": "5.6. Core components",
                "file": "./500.components/560.core-components.md"
            },
            {
                "title": "5.7. Wrapper",
                "file": "./500.components/570.component-wrapper.md"
            },
            {
                "title": "5.8. Form Wrapper",
                "file": "./500.components/580.component-form-wrapper.md"
            }
        ]
    },
    {
        "title": "6. Services",
        "file": "./600.services/600.services.md",
        "children": [
            {
                "title": "6.1. Form Wrapper",
                "file": "./600.services/610.config-servece.md"
            }
        ]
    },
    {
        "title": "7. Styles",
        "file": "./700.styles/700.styles.md"
    },
    {
        "title": "8. Misc",
        "file": "./800.misc/800.misc.md",
        "children": [
            {
                "title": "8.1. About Engine",
                "file": "./800.misc/810.about-engine.md"
            },
            {
                "title": "8.2. Add Fonts",
                "file": "./800.misc/820.add-fonts.md"
            },
            {
                "title": "8.3. IDE Settings",
                "file": "./800.misc/830.ide-conf.md"
            },
            {
                "title": "8.4. Favicon",
                "file": "./800.misc/840.favicon.md"
            },
            {
                "title": "8.5. Bonus images",
                "file": "./800.misc/850.bonus-images.md"
            },
            {
                "title": "8.6. Tournament images",
                "file": "./800.misc/860.tournaments-images.md"
            },
            {
                "title": "8.7. Mocks",
                "file": "./800.misc/870.mocks.md"
            }
        ]
    },
    {
        "_id": "changelogs",
        "title": "9. Change logs",
        "file": "./900.change-logs/900.change-logs.md",
        "children": [
            {
                "title": "1.6.2 (10-06-2022)",
                "file": "./900.change-logs/releases/1.6.2_10-06-2022.md"
            },
            {
                "title": "1.6.1 (09-06-2022)",
                "file": "./900.change-logs/releases/1.6.1_09-06-2022.md"
            },
            {
                "title": "1.6.0 (08-06-2022)",
                "file": "./900.change-logs/releases/1.6.0_08-06-2022.md"
            },
            {
                "title": "1.4.0 (03-06-2022)",
                "file": "./900.change-logs/releases/1.4.0_03-06-2022.md"
            },
            {
                "title": "1.3.82 (17-05-2022)",
                "file": "./900.change-logs/releases/1.3.82_17-05-2022.md"
            },
            {
                "title": "1.3.81 (28-04-2022)",
                "file": "./900.change-logs/releases/1.3.81_28-04-2022.md"
            },
            {
                "title": "1.3.80 (27-04-2022)",
                "file": "./900.change-logs/releases/1.3.80_27-04-2022.md"
            },
            {
                "title": "1.3.78 (07-04-2022)",
                "file": "./900.change-logs/releases/1.3.78_07-04-2022.md"
            },
            {
                "title": "1.3.77 (22-03-2022)",
                "file": "./900.change-logs/releases/1.3.77_22-03-2022.md"
            },
            {
                "title": "1.3.76 (21-02-2022)",
                "file": "./900.change-logs/releases/1.3.76_21-02-2022.md"
            },
            {
                "title": "1.3.75 (04-02-2022)",
                "file": "./900.change-logs/releases/1.3.75_04-02-2022.md"
            },
            {
                "title": "1.3.74 (31-01-2022)",
                "file": "./900.change-logs/releases/1.3.74_31-01-2022.md"
            },
            {
                "title": "1.3.73 (14-01-2022)",
                "file": "./900.change-logs/releases/1.3.73_14-01-2022.md"
            },
            {
                "title": "1.3.72 (10-12-2021)",
                "file": "./900.change-logs/releases/1.3.72_10-12-2021.md"
            },
            {
                "title": "1.3.71 (26-11-2021)",
                "file": "./900.change-logs/releases/1.3.71_26-11-2021.md"
            },
            {
                "title": "1.3.70 (03-11-2021)",
                "file": "./900.change-logs/releases/1.3.70_03-11-2021.md"
            },
            {
                "title": "1.3.69 (26-10-2021)",
                "file": "./900.change-logs/releases/1.3.69_26-10-2021.md"
            },
            {
                "title": "1.3.68 (08-10-2021)",
                "file": "./900.change-logs/releases/1.3.68_08-10-2021.md"
            },
            {
                "title": "1.3.67 (07-10-2021)",
                "file": "./900.change-logs/releases/1.3.67_07-10-2021.md"
            },
            {
                "title": "1.3.66 (30-09-2021)",
                "file": "./900.change-logs/releases/1.3.66_30-09-2021.md"
            },
            {
                "title": "1.3.65 (23-09-2021)",
                "file": "./900.change-logs/releases/1.3.65_23-09-2021.md"
            },
            {
                "title": "1.3.64 (23-09-2021)",
                "file": "./900.change-logs/releases/1.3.64_23-09-2021.md"
            },
            {
                "title": "1.3.63 (21-09-2021)",
                "file": "./900.change-logs/releases/1.3.63_21-09-2021.md"
            },
            {
                "title": "1.3.62 (16-09-2021)",
                "file": "./900.change-logs/releases/1.3.62_16-09-2021.md"
            },
            {
                "title": "1.3.61 (10-09-2021)",
                "file": "./900.change-logs/releases/1.3.61_10-09-2021.md"
            },
            {
                "title": "1.3.60 (07-09-2021)",
                "file": "./900.change-logs/releases/1.3.60_07-09-2021.md"
            },
            {
                "title": "1.3.59 (02-09-2021)",
                "file": "./900.change-logs/releases/1.3.59_02-09-2021.md"
            },
            {
                "title": "1.3.58 (02-09-2021)",
                "file": "./900.change-logs/releases/1.3.58_02-09-2021.md"
            },
            {
                "title": "1.3.57 (01-09-2021)",
                "file": "./900.change-logs/releases/1.3.57_01-09-2021.md"
            },
            {
                "title": "1.3.56 (27-08-2021)",
                "file": "./900.change-logs/releases/1.3.56_27-08-2021.md"
            },
            {
                "title": "1.3.55 (25-08-2021)",
                "file": "./900.change-logs/releases/1.3.55_25-08-2021.md"
            },
            {
                "title": "1.3.54 (23-08-2021)",
                "file": "./900.change-logs/releases/1.3.54_23-08-2021.md"
            },
            {
                "title": "1.3.52 (18-08-2021)",
                "file": "./900.change-logs/releases/1.3.52_18-08-2021.md"
            },
            {
                "title": "1.3.51 (17-08-2021)",
                "file": "./900.change-logs/releases/1.3.51_17-08-2021.md"
            },
            {
                "title": "1.3.50 (16-08-2021)",
                "file": "./900.change-logs/releases/1.3.50_16-08-2021.md"
            },
            {
                "title": "1.3.49 (13-08-2021)",
                "file": "./900.change-logs/releases/1.3.49_13-08-2021.md"
            },
            {
                "title": "1.3.48 (12-08-2021)",
                "file": "./900.change-logs/releases/1.3.48_12-08-2021.md"
            },
            {
                "title": "1.3.47 (11-08-2021)",
                "file": "./900.change-logs/releases/1.3.47_11-08-2021.md"
            },
            {
                "title": "1.3.46 (11-08-2021)",
                "file": "./900.change-logs/releases/1.3.46_11-08-2021.md"
            },
            {
                "title": "1.3.45 (10-08-2021)",
                "file": "./900.change-logs/releases/1.3.45_10-08-2021.md"
            },
            {
                "title": "1.3.44 (09-08-2021)",
                "file": "./900.change-logs/releases/1.3.44_09-08-2021.md"
            },
            {
                "title": "1.3.43 (09-08-2021)",
                "file": "./900.change-logs/releases/1.3.43_09-08-2021.md"
            },
            {
                "title": "1.3.42 (05-08-2021)",
                "file": "./900.change-logs/releases/1.3.42_05-08-2021.md"
            },
            {
                "title": "1.3.41 (03-08-2021)",
                "file": "./900.change-logs/releases/1.3.41_03-08-2021.md"
            },
            {
                "title": "1.3.40 (30-07-2021)",
                "file": "./900.change-logs/releases/1.3.40_30-07-2021.md"
            },
            {
                "title": "1.3.39 (29-07-2021)",
                "file": "./900.change-logs/releases/1.3.39_29-07-2021.md"
            },
            {
                "title": "1.3.38 (29-07-2021)",
                "file": "./900.change-logs/releases/1.3.38_29-07-2021.md"
            },
            {
                "title": "1.3.37 (27-07-2021)",
                "file": "./900.change-logs/releases/1.3.37_27-07-2021.md"
            },
            {
                "title": "1.3.36 (23-07-2021)",
                "file": "./900.change-logs/releases/1.3.36_23-07-2021.md"
            },
            {
                "title": "1.3.35 (22-07-2021)",
                "file": "./900.change-logs/releases/1.3.35_22-07-2021.md"
            },
            {
                "title": "1.3.34 (22-07-2021)",
                "file": "./900.change-logs/releases/1.3.34_22-07-2021.md"
            },
            {
                "title": "1.3.33 (22-07-2021)",
                "file": "./900.change-logs/releases/1.3.33_22-07-2021.md"
            },
            {
                "title": "1.3.32 (22-07-2021)",
                "file": "./900.change-logs/releases/1.3.32_22-07-2021.md"
            },
            {
                "title": "1.3.31 (21-07-2021)",
                "file": "./900.change-logs/releases/1.3.31_21-07-2021.md"
            },
            {
                "title": "1.3.30 (20-07-2021)",
                "file": "./900.change-logs/releases/1.3.30_20-07-2021.md"
            },
            {
                "title": "1.3.29 (19-07-2021)",
                "file": "./900.change-logs/releases/1.3.29_19-07-2021.md"
            },
            {
                "title": "1.3.28 (19-07-2021)",
                "file": "./900.change-logs/releases/1.3.28_19-07-2021.md"
            },
            {
                "title": "1.3.27 (19-07-2021)",
                "file": "./900.change-logs/releases/1.3.27_19-07-2021.md"
            },
            {
                "title": "1.3.26 (16-07-2021)",
                "file": "./900.change-logs/releases/1.3.26_16-07-2021.md"
            },
            {
                "title": "1.3.25 (14-07-2021)",
                "file": "./900.change-logs/releases/1.3.25_14-07-2021.md"
            },
            {
                "title": "1.3.24 (12-07-2021)",
                "file": "./900.change-logs/releases/1.3.24_12-07-2021.md"
            },
            {
                "title": "1.3.23 (12-07-2021)",
                "file": "./900.change-logs/releases/1.3.23_12-07-2021.md"
            },
            {
                "title": "1.3.22 (07-07-2021)",
                "file": "./900.change-logs/releases/1.3.22_07-07-2021.md"
            },
            {
                "title": "1.3.21 (07-07-2021)",
                "file": "./900.change-logs/releases/1.3.21_07-07-2021.md"
            },
            {
                "title": "1.3.20 (06-07-2021)",
                "file": "./900.change-logs/releases/1.3.20_06-07-2021.md"
            },
            {
                "title": "1.3.19 (06-07-2021)",
                "file": "./900.change-logs/releases/1.3.19_06-07-2021.md"
            },
            {
                "title": "1.3.18 (05-07-2021)",
                "file": "./900.change-logs/releases/1.3.18_05-07-2021.md"
            },
            {
                "title": "1.3.17 (02-07-2021)",
                "file": "./900.change-logs/releases/1.3.17_02-07-2021.md"
            },
            {
                "title": "1.3.16 (01-07-2021)",
                "file": "./900.change-logs/releases/1.3.16_01-07-2021.md"
            }
        ]
    },
    {
        "title": "10. Releases",
        "file": "../../../RELEASES.md"
    }
]